{"current_page":1,"data":[{"id":52,"code":"17PRM","name":"iPhone 17 Pro Max","sort_order":-106,"is_active":true,"created_at":"2025-09-23T08:14:08.000000Z","updated_at":"2025-09-23T08:14:08.000000Z"},{"id":51,"code":"17PRO","name":"iPhone 17 Pro","sort_order":-105,"is_active":true,"created_at":"2025-09-23T08:13:47.000000Z","updated_at":"2025-09-23T08:13:47.000000Z"},{"id":50,"code":"17AIR","name":"iPhone 17 Air","sort_order":-104,"is_active":true,"created_at":"2025-09-23T08:13:25.000000Z","updated_at":"2025-09-23T08:13:25.000000Z"},{"id":48,"code":"16PRM","name":"iPhone 16 Pro Max","sort_order":-103,"is_active":true,"created_at":"2025-09-06T10:56:00.000000Z","updated_at":"2025-09-07T02:41:01.000000Z"},{"id":41,"code":"15PRM","name":"iPhone 15 Pro Max","sort_order":-102,"is_active":true,"created_at":"2025-09-06T10:56:00.000000Z","updated_at":"2025-09-07T02:41:01.000000Z"},{"id":47,"code":"16PRO","name":"iPhone 16 Pro","sort_order":-102,"is_active":true,"created_at":"2025-09-06T10:56:00.000000Z","updated_at":"2025-09-07T02:41:01.000000Z"},{"id":46,"code":"16PLUS","name":"iPhone 16 Plus","sort_order":-101,"is_active":true,"created_at":"2025-09-06T10:56:00.000000Z","updated_at":"2025-09-07T02:41:01.000000Z"},{"id":40,"code":"15PRO","name":"iPhone 15 Pro","sort_order":-101,"is_active":true,"created_at":"2025-09-06T10:56:00.000000Z","updated_at":"2025-09-07T02:41:01.000000Z"},{"id":39,"code":"15","name":"iPhone 15","sort_order":-100,"is_active":true,"created_at":"2025-09-06T10:56:00.000000Z","updated_at":"2025-09-07T02:41:01.000000Z"},{"id":42,"code":"15PLUS","name":"iPhone 15 Plus","sort_order":-100,"is_active":true,"created_at":"2025-09-06T10:56:00.000000Z","updated_at":"2025-09-07T02:41:01.000000Z"},{"id":45,"code":"16","name":"iPhone 16","sort_order":-100,"is_active":true,"created_at":"2025-09-06T10:56:00.000000Z","updated_at":"2025-09-07T02:41:01.000000Z"},{"id":38,"code":"14PRM","name":"iPhone 14 Pro Max","sort_order":-99,"is_active":true,"created_at":"2025-09-06T10:56:00.000000Z","updated_at":"2025-09-07T02:41:01.000000Z"},{"id":37,"code":"14PRO","name":"iPhone 14 Pro","sort_order":-98,"is_active":true,"created_at":"2025-09-06T10:56:00.000000Z","updated_at":"2025-09-07T02:41:01.000000Z"},{"id":20,"code":"13PRM","name":"iPhone 13 Pro Max","sort_order":-97,"is_active":true,"created_at":"2025-09-06T10:56:00.000000Z","updated_at":"2025-09-07T02:41:01.000000Z"},{"id":19,"code":"13PRO","name":"iPhone 13 Pro","sort_order":-96,"is_active":true,"created_at":"2025-09-06T10:56:00.000000Z","updated_at":"2025-09-07T02:41:01.000000Z"},{"id":17,"code":"12PRM","name":"iPhone 12 Pro Max","sort_order":-95,"is_active":true,"created_at":"2025-09-06T10:56:00.000000Z","updated_at":"2025-09-07T02:41:01.000000Z"},{"id":16,"code":"12PRO","name":"iPhone 12 Pro","sort_order":-94,"is_active":true,"created_at":"2025-09-06T10:56:00.000000Z","updated_at":"2025-09-07T02:41:01.000000Z"},{"id":13,"code":"11PRM","name":"iPhone 11 Pro Max","sort_order":-93,"is_active":true,"created_at":"2025-09-06T10:56:00.000000Z","updated_at":"2025-09-07T02:41:01.000000Z"},{"id":12,"code":"11PRO","name":"iPhone 11 Pro","sort_order":-92,"is_active":true,"created_at":"2025-09-06T10:56:00.000000Z","updated_at":"2025-09-07T02:41:01.000000Z"},{"id":10,"code":"XSM","name":"iPhone XS Max","sort_order":-91,"is_active":true,"created_at":"2025-09-06T10:56:00.000000Z","updated_at":"2025-09-07T02:41:01.000000Z"},{"id":43,"code":"13MINI","name":"iPhone 13 Mini","sort_order":-90,"is_active":true,"created_at":"2025-09-06T10:56:00.000000Z","updated_at":"2025-09-07T02:41:01.000000Z"},{"id":35,"code":"14","name":"iPhone 14","sort_order":-1,"is_active":true,"created_at":"2025-09-06T10:56:00.000000Z","updated_at":"2025-09-07T02:41:01.000000Z"},{"id":49,"code":"16E","name":"iPhone 16E","sort_order":0,"is_active":true,"created_at":"2025-09-07T03:25:54.000000Z","updated_at":"2025-09-07T03:25:54.000000Z"},{"id":1,"code":"6","name":"iPhone 6","sort_order":1,"is_active":false,"created_at":"2025-09-06T10:56:00.000000Z","updated_at":"2025-09-07T07:12:17.000000Z"},{"id":27,"code":"6P","name":"iPhone 6 Plus","sort_order":2,"is_active":false,"created_at":"2025-09-06T10:56:00.000000Z","updated_at":"2025-09-07T07:12:23.000000Z"},{"id":2,"code":"6S","name":"iPhone 6S","sort_order":3,"is_active":true,"created_at":"2025-09-06T10:56:00.000000Z","updated_at":"2025-09-07T02:40:47.000000Z"},{"id":3,"code":"6SP","name":"iPhone 6S Plus","sort_order":4,"is_active":true,"created_at":"2025-09-06T10:56:00.000000Z","updated_at":"2025-09-07T02:41:01.000000Z"},{"id":4,"code":"7","name":"iPhone 7","sort_order":5,"is_active":true,"created_at":"2025-09-06T10:56:00.000000Z","updated_at":"2025-09-07T02:41:01.000000Z"},{"id":5,"code":"7P","name":"iPhone 7 Plus","sort_order":6,"is_active":true,"created_at":"2025-09-06T10:56:00.000000Z","updated_at":"2025-09-07T02:41:01.000000Z"},{"id":6,"code":"8","name":"iPhone 8","sort_order":7,"is_active":true,"created_at":"2025-09-06T10:56:00.000000Z","updated_at":"2025-09-07T02:41:01.000000Z"},{"id":7,"code":"8P","name":"iPhone 8 Plus","sort_order":8,"is_active":true,"created_at":"2025-09-06T10:56:00.000000Z","updated_at":"2025-09-07T02:41:01.000000Z"},{"id":29,"code":"X","name":"iPhone X","sort_order":9,"is_active":true,"created_at":"2025-09-06T10:56:00.000000Z","updated_at":"2025-09-07T02:41:01.000000Z"},{"id":8,"code":"XR","name":"iPhone XR","sort_order":9,"is_active":true,"created_at":"2025-09-06T10:56:00.000000Z","updated_at":"2025-09-07T02:41:01.000000Z"},{"id":9,"code":"XS","name":"iPhone XS","sort_order":10,"is_active":true,"created_at":"2025-09-06T10:56:00.000000Z","updated_at":"2025-09-07T02:41:01.000000Z"},{"id":11,"code":"11","name":"iPhone 11","sort_order":12,"is_active":true,"created_at":"2025-09-06T10:56:00.000000Z","updated_at":"2025-09-07T02:41:01.000000Z"},{"id":14,"code":"12M","name":"iPhone 12 Mini","sort_order":15,"is_active":true,"created_at":"2025-09-06T10:56:00.000000Z","updated_at":"2025-09-07T02:41:01.000000Z"},{"id":15,"code":"12","name":"iPhone 12","sort_order":16,"is_active":true,"created_at":"2025-09-06T10:56:00.000000Z","updated_at":"2025-09-07T02:41:01.000000Z"},{"id":36,"code":"14PLUS","name":"iPhone 14 Plus","sort_order":18,"is_active":true,"created_at":"2025-09-06T10:56:00.000000Z","updated_at":"2025-09-07T02:41:01.000000Z"},{"id":18,"code":"13","name":"iPhone 13","sort_order":19,"is_active":true,"created_at":"2025-09-06T10:56:00.000000Z","updated_at":"2025-09-07T02:41:01.000000Z"},{"id":21,"code":"WATCH","name":"Apple Watch","sort_order":22,"is_active":true,"created_at":"2025-09-06T10:56:00.000000Z","updated_at":"2025-09-07T02:41:01.000000Z"},{"id":22,"code":"AIRPOD","name":"AirPod","sort_order":23,"is_active":true,"created_at":"2025-09-06T10:56:00.000000Z","updated_at":"2025-09-07T02:41:01.000000Z"},{"id":23,"code":"AIRTAG","name":"AirTag","sort_order":24,"is_active":true,"created_at":"2025-09-06T10:56:00.000000Z","updated_at":"2025-09-07T02:41:01.000000Z"},{"id":24,"code":"SE","name":"iPhone SE","sort_order":25,"is_active":true,"created_at":"2025-09-06T10:56:00.000000Z","updated_at":"2025-09-07T02:41:01.000000Z"},{"id":25,"code":"SE2","name":"iPhone SE 2","sort_order":26,"is_active":true,"created_at":"2025-09-06T10:56:00.000000Z","updated_at":"2025-09-07T02:41:01.000000Z"},{"id":30,"code":"Laptop","name":"Laptop","sort_order":26,"is_active":true,"created_at":"2025-09-06T10:56:00.000000Z","updated_at":"2025-09-07T02:41:01.000000Z"},{"id":26,"code":"IPAD","name":"iPad","sort_order":27,"is_active":true,"created_at":"2025-09-06T10:56:00.000000Z","updated_at":"2025-09-07T02:41:01.000000Z"},{"id":32,"code":"SE3","name":"iPhone SE 3","sort_order":27,"is_active":true,"created_at":"2025-09-06T10:56:00.000000Z","updated_at":"2025-09-07T02:41:01.000000Z"},{"id":31,"code":"Android","name":"Android","sort_order":27,"is_active":true,"created_at":"2025-09-06T10:56:00.000000Z","updated_at":"2025-09-07T02:41:01.000000Z"},{"id":28,"code":"SamSung","name":"Sam Sung","sort_order":28,"is_active":true,"created_at":"2025-09-06T10:56:00.000000Z","updated_at":"2025-09-07T02:41:01.000000Z"},{"id":44,"code":"5SE","name":"iPhone 5 SE","sort_order":60,"is_active":false,"created_at":"2025-09-06T10:56:00.000000Z","updated_at":"2025-09-07T03:25:31.000000Z"}],"first_page_url":"http:\/\/192.168.10.10:8080\/api\/admin\/devices?page=1","from":1,"last_page":1,"last_page_url":"http:\/\/192.168.10.10:8080\/api\/admin\/devices?page=1","links":[{"url":null,"label":"&laquo; Previous","active":false},{"url":"http:\/\/192.168.10.10:8080\/api\/admin\/devices?page=1","label":"1","active":true},{"url":null,"label":"Next &raquo;","active":false}],"next_page_url":null,"path":"http:\/\/192.168.10.10:8080\/api\/admin\/devices","per_page":100,"prev_page_url":null,"to":50,"total":50}